vhrun3/__init__.py
vhrun3/__main__.py
vhrun3/app/__init__.py
vhrun3/app/main.py
vhrun3/app/routers/__init__.py
vhrun3/app/routers/debug.py
vhrun3/app/routers/debugtalk.py
vhrun3/app/routers/deps.py
vhrun3/builtin/__init__.py
vhrun3/builtin/comparators.py
vhrun3/builtin/functions.py
vhrun3/cli.py
vhrun3/client.py
vhrun3/compat.py
vhrun3/exceptions.py
vhrun3/ext/__init__.py
vhrun3/ext/har2case/__init__.py
vhrun3/ext/har2case/core.py
vhrun3/ext/har2case/utils.py
vhrun3/ext/locust/__init__.py
vhrun3/ext/locust/locustfile.py
vhrun3/ext/uploader/__init__.py
vhrun3/loader.py
vhrun3/make.py
vhrun3/models.py
vhrun3/parser.py
vhrun3/report/__init__.py
vhrun3/report/aggregate.py
vhrun3/report/allure_report/__init__.py
vhrun3/report/allure_report/allure_step.py
vhrun3/report/compat.py
vhrun3/report/html/__init__.py
vhrun3/report/html/gen_report.py
vhrun3/report/html/template.html
vhrun3/report/stringify.py
vhrun3/response.py
vhrun3/runner.py
vhrun3/scaffold.py
vhrun3/testcase.py
vhrun3/utils.py
vhrun3-1.3.3.dist-info/entry_points.txt
vhrun3-1.3.3.dist-info/WHEEL
vhrun3-1.3.3.dist-info/METADATA
vhrun3-1.3.3.dist-info/RECORD
