Metadata-Version: 2.1
Name: vhrun3
Version: 1.3.3
Summary: 
Author: tigerjlx
Requires-Python: >=3.7,<4.0
Classifier: Programming Language :: Python :: 3
Classifier: Programming Language :: Python :: 3.10
Classifier: Programming Language :: Python :: 3.7
Classifier: Programming Language :: Python :: 3.8
Classifier: Programming Language :: Python :: 3.9
Requires-Dist: httprunner (>=3.1.6,<4.0.0)
